monzo_api_wrapper/__init__.py
monzo_api_wrapper/get_balances.py
monzo_api_wrapper/get_transactions.py
monzo_api_wrapper/upload_balances.py
monzo_api_wrapper/upload_transactions.py
monzo_api_wrapper/utils/__init__.py
monzo_api_wrapper/utils/custom_logger.py
monzo_api_wrapper/utils/db.py
monzo_api_wrapper/utils/sql_templates.py
tests/test_get_transactions.py
monzo_api_wrapper-0.1.1.dist-info/LICENSE
monzo_api_wrapper-0.1.1.dist-info/METADATA
monzo_api_wrapper-0.1.1.dist-info/WHEEL
monzo_api_wrapper-0.1.1.dist-info/top_level.txt
monzo_api_wrapper-0.1.1.dist-info/RECORD
