Metadata-Version: 2.1
Name: monzo_api_wrapper
Version: 0.1.1
Summary: Wrapper for monzo-api package to fetch Monzo transactions and store them in a database.
Author-email: Elias Benaddou Idrissi <e.benaddou@hey.com>
Project-URL: Homepage, https://eliasbenaddou.github.io/monzo-api-wrapper/
Project-URL: Repository, https://github.com/eliasbenaddou/monzo-api-wrapper
Project-URL: Documentation, https://eliasbenaddou.github.io/monzo-api-wrapper/
Keywords: python
Classifier: Intended Audience :: Developers
Classifier: Programming Language :: Python
Classifier: Programming Language :: Python :: 3
Classifier: Programming Language :: Python :: 3.9
Classifier: Programming Language :: Python :: 3.10
Classifier: Programming Language :: Python :: 3.11
Classifier: Programming Language :: Python :: 3.12
Classifier: Programming Language :: Python :: 3.13
Classifier: Topic :: Software Development :: Libraries :: Python Modules
Requires-Python: <4.0,>=3.9
License-File: LICENSE
Requires-Dist: pandas >=2.2.3
Requires-Dist: sqlalchemy >=2.0.36
Requires-Dist: loguru >=0.7.2
Requires-Dist: monzo-api >=1.1.0
Requires-Dist: numpy >=1.26.4
